{
  "last_fetch_jst": "2026-06-30 03:24:27",
  "camera_count": 42,
  "cameras": [
    {
      "pid": "01",
      "size": 45450
    },
    {
      "pid": "02",
      "size": 62949
    },
    {
      "pid": "03",
      "size": 61793
    },
    {
      "pid": "04",
      "size": 56641
    },
    {
      "pid": "05",
      "size": 64922
    },
    {
      "pid": "06",
      "size": 46529
    },
    {
      "pid": "07",
      "size": 62611
    },
    {
      "pid": "08",
      "size": 48901
    },
    {
      "pid": "09",
      "size": 36030
    },
    {
      "pid": "10",
      "size": 47301
    },
    {
      "pid": "11",
      "size": 87461
    },
    {
      "pid": "12",
      "size": 79621
    },
    {
      "pid": "13",
      "size": 33808
    },
    {
      "pid": "14",
      "size": 134423
    },
    {
      "pid": "15",
      "size": 48421
    },
    {
      "pid": "16",
      "size": 82493
    },
    {
      "pid": "17",
      "size": 30322
    },
    {
      "pid": "18",
      "size": 34581
    },
    {
      "pid": "19",
      "size": 37063
    },
    {
      "pid": "20",
      "size": 52709
    },
    {
      "pid": "21",
      "size": 15692
    },
    {
      "pid": "22",
      "size": 69666
    },
    {
      "pid": "23",
      "size": 48438
    },
    {
      "pid": "24",
      "size": 48101
    },
    {
      "pid": "25",
      "size": 60248
    },
    {
      "pid": "26",
      "size": 134423
    },
    {
      "pid": "27",
      "size": 134423
    },
    {
      "pid": "28",
      "size": 134423
    },
    {
      "pid": "29",
      "size": 134423
    },
    {
      "pid": "41",
      "size": 65020
    },
    {
      "pid": "42",
      "size": 44587
    },
    {
      "pid": "43",
      "size": 63434
    },
    {
      "pid": "44",
      "size": 20535
    },
    {
      "pid": "45",
      "size": 134423
    },
    {
      "pid": "49",
      "size": 47027
    },
    {
      "pid": "50",
      "size": 20535
    },
    {
      "pid": "51",
      "size": 20535
    },
    {
      "pid": "52",
      "size": 42492
    },
    {
      "pid": "53",
      "size": 67916
    },
    {
      "pid": "64",
      "size": 48223
    },
    {
      "pid": "65",
      "size": 20535
    },
    {
      "pid": "66",
      "size": 20535
    }
  ],
  "extra_cameras": [
    {
      "key": "okinawa-city-hija",
      "name": "比謝川",
      "loc": "沖縄市（水位監視）",
      "size": 39996
    },
    {
      "key": "okinawa-city-awase1",
      "name": "泡瀬川①",
      "loc": "沖縄市（水位監視）",
      "size": 23874
    },
    {
      "key": "okinawa-city-awase2",
      "name": "泡瀬川②",
      "loc": "沖縄市（水位監視）",
      "size": 23974
    }
  ]
}