{
  "last_fetch_jst": "2026-07-20 08:10:31",
  "camera_count": 42,
  "cameras": [
    {
      "pid": "01",
      "size": 69520
    },
    {
      "pid": "02",
      "size": 81046
    },
    {
      "pid": "03",
      "size": 73722
    },
    {
      "pid": "04",
      "size": 115609
    },
    {
      "pid": "05",
      "size": 96204
    },
    {
      "pid": "06",
      "size": 96116
    },
    {
      "pid": "07",
      "size": 109349
    },
    {
      "pid": "08",
      "size": 88784
    },
    {
      "pid": "09",
      "size": 92975
    },
    {
      "pid": "10",
      "size": 51968
    },
    {
      "pid": "11",
      "size": 82943
    },
    {
      "pid": "12",
      "size": 93028
    },
    {
      "pid": "13",
      "size": 78757
    },
    {
      "pid": "14",
      "size": 134423
    },
    {
      "pid": "15",
      "size": 77860
    },
    {
      "pid": "16",
      "size": 51800
    },
    {
      "pid": "17",
      "size": 62647
    },
    {
      "pid": "18",
      "size": 91028
    },
    {
      "pid": "19",
      "size": 85388
    },
    {
      "pid": "20",
      "size": 38284
    },
    {
      "pid": "21",
      "size": 15692
    },
    {
      "pid": "22",
      "size": 98861
    },
    {
      "pid": "23",
      "size": 98219
    },
    {
      "pid": "24",
      "size": 109058
    },
    {
      "pid": "25",
      "size": 97797
    },
    {
      "pid": "26",
      "size": 134423
    },
    {
      "pid": "27",
      "size": 134423
    },
    {
      "pid": "28",
      "size": 134423
    },
    {
      "pid": "29",
      "size": 134423
    },
    {
      "pid": "41",
      "size": 97941
    },
    {
      "pid": "42",
      "size": 70530
    },
    {
      "pid": "43",
      "size": 94194
    },
    {
      "pid": "44",
      "size": 20535
    },
    {
      "pid": "45",
      "size": 134423
    },
    {
      "pid": "49",
      "size": 66442
    },
    {
      "pid": "50",
      "size": 20535
    },
    {
      "pid": "51",
      "size": 20535
    },
    {
      "pid": "52",
      "size": 105401
    },
    {
      "pid": "53",
      "size": 101495
    },
    {
      "pid": "64",
      "size": 92529
    },
    {
      "pid": "65",
      "size": 20535
    },
    {
      "pid": "66",
      "size": 20535
    }
  ],
  "extra_cameras": [
    {
      "key": "okinawa-city-hija",
      "name": "比謝川",
      "loc": "沖縄市（水位監視）",
      "size": 40456
    },
    {
      "key": "okinawa-city-awase1",
      "name": "泡瀬川①",
      "loc": "沖縄市（水位監視）",
      "size": 24540
    },
    {
      "key": "okinawa-city-awase2",
      "name": "泡瀬川②",
      "loc": "沖縄市（水位監視）",
      "size": 24079
    }
  ]
}