{
  "last_fetch_jst": "2026-04-27 15:17:21",
  "camera_count": 42,
  "cameras": [
    {
      "pid": "01",
      "size": 49853
    },
    {
      "pid": "02",
      "size": 95421
    },
    {
      "pid": "03",
      "size": 91512
    },
    {
      "pid": "04",
      "size": 105850
    },
    {
      "pid": "05",
      "size": 95041
    },
    {
      "pid": "06",
      "size": 110714
    },
    {
      "pid": "07",
      "size": 100902
    },
    {
      "pid": "08",
      "size": 89906
    },
    {
      "pid": "09",
      "size": 98231
    },
    {
      "pid": "10",
      "size": 59654
    },
    {
      "pid": "11",
      "size": 99999
    },
    {
      "pid": "12",
      "size": 93706
    },
    {
      "pid": "13",
      "size": 73081
    },
    {
      "pid": "14",
      "size": 134423
    },
    {
      "pid": "15",
      "size": 96447
    },
    {
      "pid": "16",
      "size": 100353
    },
    {
      "pid": "17",
      "size": 93185
    },
    {
      "pid": "18",
      "size": 110197
    },
    {
      "pid": "19",
      "size": 93566
    },
    {
      "pid": "20",
      "size": 66388
    },
    {
      "pid": "21",
      "size": 15692
    },
    {
      "pid": "22",
      "size": 114937
    },
    {
      "pid": "23",
      "size": 111395
    },
    {
      "pid": "24",
      "size": 124242
    },
    {
      "pid": "25",
      "size": 85073
    },
    {
      "pid": "26",
      "size": 134423
    },
    {
      "pid": "27",
      "size": 134423
    },
    {
      "pid": "28",
      "size": 134423
    },
    {
      "pid": "29",
      "size": 134423
    },
    {
      "pid": "41",
      "size": 99202
    },
    {
      "pid": "42",
      "size": 75921
    },
    {
      "pid": "43",
      "size": 5463
    },
    {
      "pid": "44",
      "size": 20535
    },
    {
      "pid": "45",
      "size": 134423
    },
    {
      "pid": "49",
      "size": 5463
    },
    {
      "pid": "50",
      "size": 20535
    },
    {
      "pid": "51",
      "size": 20535
    },
    {
      "pid": "52",
      "size": 104193
    },
    {
      "pid": "53",
      "size": 115646
    },
    {
      "pid": "64",
      "size": 5463
    },
    {
      "pid": "65",
      "size": 20535
    },
    {
      "pid": "66",
      "size": 20535
    }
  ],
  "extra_cameras": [
    {
      "key": "okinawa-city-hija",
      "name": "比謝川",
      "loc": "沖縄市（水位監視）",
      "size": 39054
    },
    {
      "key": "okinawa-city-awase1",
      "name": "泡瀬川①",
      "loc": "沖縄市（水位監視）",
      "size": 24417
    },
    {
      "key": "okinawa-city-awase2",
      "name": "泡瀬川②",
      "loc": "沖縄市（水位監視）",
      "size": 24154
    }
  ]
}