{
  "last_fetch_jst": "2026-06-27 21:05:03",
  "camera_count": 42,
  "cameras": [
    {
      "pid": "01",
      "size": 71077
    },
    {
      "pid": "02",
      "size": 66384
    },
    {
      "pid": "03",
      "size": 55634
    },
    {
      "pid": "04",
      "size": 57326
    },
    {
      "pid": "05",
      "size": 62548
    },
    {
      "pid": "06",
      "size": 44294
    },
    {
      "pid": "07",
      "size": 65064
    },
    {
      "pid": "08",
      "size": 47322
    },
    {
      "pid": "09",
      "size": 38668
    },
    {
      "pid": "10",
      "size": 42473
    },
    {
      "pid": "11",
      "size": 81374
    },
    {
      "pid": "12",
      "size": 67377
    },
    {
      "pid": "13",
      "size": 34296
    },
    {
      "pid": "14",
      "size": 134423
    },
    {
      "pid": "15",
      "size": 37802
    },
    {
      "pid": "16",
      "size": 75772
    },
    {
      "pid": "17",
      "size": 36141
    },
    {
      "pid": "18",
      "size": 33267
    },
    {
      "pid": "19",
      "size": 48340
    },
    {
      "pid": "20",
      "size": 54432
    },
    {
      "pid": "21",
      "size": 15692
    },
    {
      "pid": "22",
      "size": 70809
    },
    {
      "pid": "23",
      "size": 49128
    },
    {
      "pid": "24",
      "size": 59702
    },
    {
      "pid": "25",
      "size": 49206
    },
    {
      "pid": "26",
      "size": 134423
    },
    {
      "pid": "27",
      "size": 134423
    },
    {
      "pid": "28",
      "size": 134423
    },
    {
      "pid": "29",
      "size": 134423
    },
    {
      "pid": "41",
      "size": 65073
    },
    {
      "pid": "42",
      "size": 49792
    },
    {
      "pid": "43",
      "size": 62144
    },
    {
      "pid": "44",
      "size": 20535
    },
    {
      "pid": "45",
      "size": 134423
    },
    {
      "pid": "49",
      "size": 47806
    },
    {
      "pid": "50",
      "size": 20535
    },
    {
      "pid": "51",
      "size": 20535
    },
    {
      "pid": "52",
      "size": 45168
    },
    {
      "pid": "53",
      "size": 67868
    },
    {
      "pid": "64",
      "size": 45117
    },
    {
      "pid": "65",
      "size": 20535
    },
    {
      "pid": "66",
      "size": 20535
    }
  ],
  "extra_cameras": [
    {
      "key": "okinawa-city-hija",
      "name": "比謝川",
      "loc": "沖縄市（水位監視）",
      "size": 40071
    },
    {
      "key": "okinawa-city-awase1",
      "name": "泡瀬川①",
      "loc": "沖縄市（水位監視）",
      "size": 24360
    },
    {
      "key": "okinawa-city-awase2",
      "name": "泡瀬川②",
      "loc": "沖縄市（水位監視）",
      "size": 23935
    }
  ]
}