{
  "last_fetch_jst": "2026-04-03 03:08:31",
  "camera_count": 42,
  "cameras": [
    {
      "pid": "01",
      "size": 65417
    },
    {
      "pid": "02",
      "size": 56209
    },
    {
      "pid": "03",
      "size": 58773
    },
    {
      "pid": "04",
      "size": 45398
    },
    {
      "pid": "05",
      "size": 60421
    },
    {
      "pid": "06",
      "size": 39147
    },
    {
      "pid": "07",
      "size": 58981
    },
    {
      "pid": "08",
      "size": 47755
    },
    {
      "pid": "09",
      "size": 25352
    },
    {
      "pid": "10",
      "size": 38639
    },
    {
      "pid": "11",
      "size": 92106
    },
    {
      "pid": "12",
      "size": 59575
    },
    {
      "pid": "13",
      "size": 25125
    },
    {
      "pid": "14",
      "size": 134423
    },
    {
      "pid": "15",
      "size": 52890
    },
    {
      "pid": "16",
      "size": 5463
    },
    {
      "pid": "17",
      "size": 48878
    },
    {
      "pid": "18",
      "size": 30994
    },
    {
      "pid": "19",
      "size": 41507
    },
    {
      "pid": "20",
      "size": 53830
    },
    {
      "pid": "21",
      "size": 15692
    },
    {
      "pid": "22",
      "size": 55992
    },
    {
      "pid": "23",
      "size": 45829
    },
    {
      "pid": "24",
      "size": 39350
    },
    {
      "pid": "25",
      "size": 44787
    },
    {
      "pid": "26",
      "size": 134423
    },
    {
      "pid": "27",
      "size": 134423
    },
    {
      "pid": "28",
      "size": 134423
    },
    {
      "pid": "29",
      "size": 134423
    },
    {
      "pid": "41",
      "size": 70273
    },
    {
      "pid": "42",
      "size": 50886
    },
    {
      "pid": "43",
      "size": 5463
    },
    {
      "pid": "44",
      "size": 20535
    },
    {
      "pid": "45",
      "size": 134423
    },
    {
      "pid": "49",
      "size": 5463
    },
    {
      "pid": "50",
      "size": 20535
    },
    {
      "pid": "51",
      "size": 20535
    },
    {
      "pid": "52",
      "size": 44229
    },
    {
      "pid": "53",
      "size": 71118
    },
    {
      "pid": "64",
      "size": 5463
    },
    {
      "pid": "65",
      "size": 20535
    },
    {
      "pid": "66",
      "size": 20535
    }
  ],
  "extra_cameras": [
    {
      "key": "okinawa-city-hija",
      "name": "比謝川",
      "loc": "沖縄市（水位監視）",
      "size": 39954
    },
    {
      "key": "okinawa-city-awase1",
      "name": "泡瀬川①",
      "loc": "沖縄市（水位監視）",
      "size": 23813
    },
    {
      "key": "okinawa-city-awase2",
      "name": "泡瀬川②",
      "loc": "沖縄市（水位監視）",
      "size": 24504
    }
  ]
}