{
  "last_fetch_jst": "2026-04-01 23:52:00",
  "camera_count": 42,
  "cameras": [
    {
      "pid": "01",
      "size": 43733
    },
    {
      "pid": "02",
      "size": 54294
    },
    {
      "pid": "03",
      "size": 79417
    },
    {
      "pid": "04",
      "size": 48497
    },
    {
      "pid": "05",
      "size": 60774
    },
    {
      "pid": "06",
      "size": 35634
    },
    {
      "pid": "07",
      "size": 64489
    },
    {
      "pid": "08",
      "size": 47780
    },
    {
      "pid": "09",
      "size": 27261
    },
    {
      "pid": "10",
      "size": 36551
    },
    {
      "pid": "11",
      "size": 86001
    },
    {
      "pid": "12",
      "size": 55706
    },
    {
      "pid": "13",
      "size": 25055
    },
    {
      "pid": "14",
      "size": 134423
    },
    {
      "pid": "15",
      "size": 47794
    },
    {
      "pid": "16",
      "size": 5463
    },
    {
      "pid": "17",
      "size": 41818
    },
    {
      "pid": "18",
      "size": 30263
    },
    {
      "pid": "19",
      "size": 41778
    },
    {
      "pid": "20",
      "size": 60929
    },
    {
      "pid": "21",
      "size": 15692
    },
    {
      "pid": "22",
      "size": 55526
    },
    {
      "pid": "23",
      "size": 45953
    },
    {
      "pid": "24",
      "size": 62280
    },
    {
      "pid": "25",
      "size": 36330
    },
    {
      "pid": "26",
      "size": 134423
    },
    {
      "pid": "27",
      "size": 134423
    },
    {
      "pid": "28",
      "size": 134423
    },
    {
      "pid": "29",
      "size": 134423
    },
    {
      "pid": "41",
      "size": 65965
    },
    {
      "pid": "42",
      "size": 50929
    },
    {
      "pid": "43",
      "size": 5463
    },
    {
      "pid": "44",
      "size": 20535
    },
    {
      "pid": "45",
      "size": 134423
    },
    {
      "pid": "49",
      "size": 5463
    },
    {
      "pid": "50",
      "size": 20535
    },
    {
      "pid": "51",
      "size": 20535
    },
    {
      "pid": "52",
      "size": 45617
    },
    {
      "pid": "53",
      "size": 70049
    },
    {
      "pid": "64",
      "size": 5463
    },
    {
      "pid": "65",
      "size": 20535
    },
    {
      "pid": "66",
      "size": 20535
    }
  ],
  "extra_cameras": [
    {
      "key": "okinawa-city-hija",
      "name": "比謝川",
      "loc": "沖縄市（水位監視）",
      "size": 40532
    },
    {
      "key": "okinawa-city-awase1",
      "name": "泡瀬川①",
      "loc": "沖縄市（水位監視）",
      "size": 23087
    },
    {
      "key": "okinawa-city-awase2",
      "name": "泡瀬川②",
      "loc": "沖縄市（水位監視）",
      "size": 23908
    }
  ]
}