{
  "last_fetch_jst": "2026-05-04 05:26:10",
  "camera_count": 42,
  "cameras": [
    {
      "pid": "01",
      "size": 62383
    },
    {
      "pid": "02",
      "size": 58840
    },
    {
      "pid": "03",
      "size": 56269
    },
    {
      "pid": "04",
      "size": 46386
    },
    {
      "pid": "05",
      "size": 53220
    },
    {
      "pid": "06",
      "size": 35693
    },
    {
      "pid": "07",
      "size": 63638
    },
    {
      "pid": "08",
      "size": 43595
    },
    {
      "pid": "09",
      "size": 23220
    },
    {
      "pid": "10",
      "size": 31359
    },
    {
      "pid": "11",
      "size": 86109
    },
    {
      "pid": "12",
      "size": 47160
    },
    {
      "pid": "13",
      "size": 23159
    },
    {
      "pid": "14",
      "size": 134423
    },
    {
      "pid": "15",
      "size": 39742
    },
    {
      "pid": "16",
      "size": 72101
    },
    {
      "pid": "17",
      "size": 44389
    },
    {
      "pid": "18",
      "size": 28951
    },
    {
      "pid": "19",
      "size": 34225
    },
    {
      "pid": "20",
      "size": 48282
    },
    {
      "pid": "21",
      "size": 15692
    },
    {
      "pid": "22",
      "size": 59268
    },
    {
      "pid": "23",
      "size": 45679
    },
    {
      "pid": "24",
      "size": 60691
    },
    {
      "pid": "25",
      "size": 43052
    },
    {
      "pid": "26",
      "size": 134423
    },
    {
      "pid": "27",
      "size": 134423
    },
    {
      "pid": "28",
      "size": 134423
    },
    {
      "pid": "29",
      "size": 134423
    },
    {
      "pid": "41",
      "size": 71750
    },
    {
      "pid": "42",
      "size": 51453
    },
    {
      "pid": "43",
      "size": 5463
    },
    {
      "pid": "44",
      "size": 20535
    },
    {
      "pid": "45",
      "size": 134423
    },
    {
      "pid": "49",
      "size": 5463
    },
    {
      "pid": "50",
      "size": 20535
    },
    {
      "pid": "51",
      "size": 20535
    },
    {
      "pid": "52",
      "size": 55674
    },
    {
      "pid": "53",
      "size": 63567
    },
    {
      "pid": "64",
      "size": 5463
    },
    {
      "pid": "65",
      "size": 20535
    },
    {
      "pid": "66",
      "size": 20535
    }
  ],
  "extra_cameras": [
    {
      "key": "okinawa-city-hija",
      "name": "比謝川",
      "loc": "沖縄市（水位監視）",
      "size": 34480
    },
    {
      "key": "okinawa-city-awase1",
      "name": "泡瀬川①",
      "loc": "沖縄市（水位監視）",
      "size": 24209
    },
    {
      "key": "okinawa-city-awase2",
      "name": "泡瀬川②",
      "loc": "沖縄市（水位監視）",
      "size": 24569
    }
  ]
}