{
  "last_fetch_jst": "2026-03-13 14:06:41",
  "camera_count": 42,
  "cameras": [
    {
      "pid": "01",
      "size": 47210
    },
    {
      "pid": "02",
      "size": 92113
    },
    {
      "pid": "03",
      "size": 93965
    },
    {
      "pid": "04",
      "size": 113469
    },
    {
      "pid": "05",
      "size": 94996
    },
    {
      "pid": "06",
      "size": 104860
    },
    {
      "pid": "07",
      "size": 105837
    },
    {
      "pid": "08",
      "size": 92559
    },
    {
      "pid": "09",
      "size": 95040
    },
    {
      "pid": "10",
      "size": 61578
    },
    {
      "pid": "11",
      "size": 90480
    },
    {
      "pid": "12",
      "size": 92579
    },
    {
      "pid": "13",
      "size": 78002
    },
    {
      "pid": "14",
      "size": 134423
    },
    {
      "pid": "15",
      "size": 94980
    },
    {
      "pid": "16",
      "size": 5463
    },
    {
      "pid": "17",
      "size": 104512
    },
    {
      "pid": "18",
      "size": 113700
    },
    {
      "pid": "19",
      "size": 97085
    },
    {
      "pid": "20",
      "size": 68312
    },
    {
      "pid": "21",
      "size": 15692
    },
    {
      "pid": "22",
      "size": 117004
    },
    {
      "pid": "23",
      "size": 103834
    },
    {
      "pid": "24",
      "size": 114865
    },
    {
      "pid": "25",
      "size": 97958
    },
    {
      "pid": "26",
      "size": 134423
    },
    {
      "pid": "27",
      "size": 134423
    },
    {
      "pid": "28",
      "size": 134423
    },
    {
      "pid": "29",
      "size": 134423
    },
    {
      "pid": "41",
      "size": 112808
    },
    {
      "pid": "42",
      "size": 92685
    },
    {
      "pid": "43",
      "size": 5463
    },
    {
      "pid": "44",
      "size": 20535
    },
    {
      "pid": "45",
      "size": 134423
    },
    {
      "pid": "49",
      "size": 5463
    },
    {
      "pid": "50",
      "size": 20535
    },
    {
      "pid": "51",
      "size": 20535
    },
    {
      "pid": "52",
      "size": 106306
    },
    {
      "pid": "53",
      "size": 119699
    },
    {
      "pid": "64",
      "size": 5463
    },
    {
      "pid": "65",
      "size": 20535
    },
    {
      "pid": "66",
      "size": 20535
    }
  ],
  "extra_cameras": [
    {
      "key": "okinawa-city-hija",
      "name": "比謝川",
      "loc": "沖縄市（水位監視）",
      "size": 44125
    },
    {
      "key": "okinawa-city-awase1",
      "name": "泡瀬川①",
      "loc": "沖縄市（水位監視）",
      "size": 24187
    },
    {
      "key": "okinawa-city-awase2",
      "name": "泡瀬川②",
      "loc": "沖縄市（水位監視）",
      "size": 24199
    }
  ]
}