{
  "last_fetch_jst": "2026-03-14 18:52:44",
  "camera_count": 42,
  "cameras": [
    {
      "pid": "01",
      "size": 51333
    },
    {
      "pid": "02",
      "size": 74303
    },
    {
      "pid": "03",
      "size": 92360
    },
    {
      "pid": "04",
      "size": 96244
    },
    {
      "pid": "05",
      "size": 76769
    },
    {
      "pid": "06",
      "size": 99405
    },
    {
      "pid": "07",
      "size": 87990
    },
    {
      "pid": "08",
      "size": 83866
    },
    {
      "pid": "09",
      "size": 95988
    },
    {
      "pid": "10",
      "size": 51942
    },
    {
      "pid": "11",
      "size": 76253
    },
    {
      "pid": "12",
      "size": 55887
    },
    {
      "pid": "13",
      "size": 50333
    },
    {
      "pid": "14",
      "size": 134423
    },
    {
      "pid": "15",
      "size": 5463
    },
    {
      "pid": "16",
      "size": 5463
    },
    {
      "pid": "17",
      "size": 84580
    },
    {
      "pid": "18",
      "size": 82831
    },
    {
      "pid": "19",
      "size": 90073
    },
    {
      "pid": "20",
      "size": 57386
    },
    {
      "pid": "21",
      "size": 15692
    },
    {
      "pid": "22",
      "size": 90092
    },
    {
      "pid": "23",
      "size": 91885
    },
    {
      "pid": "24",
      "size": 101088
    },
    {
      "pid": "25",
      "size": 83893
    },
    {
      "pid": "26",
      "size": 134423
    },
    {
      "pid": "27",
      "size": 134423
    },
    {
      "pid": "28",
      "size": 134423
    },
    {
      "pid": "29",
      "size": 134423
    },
    {
      "pid": "41",
      "size": 77063
    },
    {
      "pid": "42",
      "size": 71368
    },
    {
      "pid": "43",
      "size": 5463
    },
    {
      "pid": "44",
      "size": 20535
    },
    {
      "pid": "45",
      "size": 134423
    },
    {
      "pid": "49",
      "size": 5463
    },
    {
      "pid": "50",
      "size": 20535
    },
    {
      "pid": "51",
      "size": 20535
    },
    {
      "pid": "52",
      "size": 102616
    },
    {
      "pid": "53",
      "size": 104944
    },
    {
      "pid": "64",
      "size": 5463
    },
    {
      "pid": "65",
      "size": 20535
    },
    {
      "pid": "66",
      "size": 20535
    }
  ],
  "extra_cameras": [
    {
      "key": "okinawa-city-hija",
      "name": "比謝川",
      "loc": "沖縄市（水位監視）",
      "size": 34885
    },
    {
      "key": "okinawa-city-awase1",
      "name": "泡瀬川①",
      "loc": "沖縄市（水位監視）",
      "size": 24686
    },
    {
      "key": "okinawa-city-awase2",
      "name": "泡瀬川②",
      "loc": "沖縄市（水位監視）",
      "size": 24309
    }
  ]
}