{
  "last_fetch_jst": "2026-06-27 11:03:14",
  "camera_count": 42,
  "cameras": [
    {
      "pid": "01",
      "size": 88496
    },
    {
      "pid": "02",
      "size": 95129
    },
    {
      "pid": "03",
      "size": 83550
    },
    {
      "pid": "04",
      "size": 114524
    },
    {
      "pid": "05",
      "size": 92796
    },
    {
      "pid": "06",
      "size": 105201
    },
    {
      "pid": "07",
      "size": 119597
    },
    {
      "pid": "08",
      "size": 91115
    },
    {
      "pid": "09",
      "size": 111629
    },
    {
      "pid": "10",
      "size": 71548
    },
    {
      "pid": "11",
      "size": 83795
    },
    {
      "pid": "12",
      "size": 93838
    },
    {
      "pid": "13",
      "size": 85593
    },
    {
      "pid": "14",
      "size": 134423
    },
    {
      "pid": "15",
      "size": 90630
    },
    {
      "pid": "16",
      "size": 91413
    },
    {
      "pid": "17",
      "size": 85371
    },
    {
      "pid": "18",
      "size": 112656
    },
    {
      "pid": "19",
      "size": 101065
    },
    {
      "pid": "20",
      "size": 58947
    },
    {
      "pid": "21",
      "size": 15692
    },
    {
      "pid": "22",
      "size": 119629
    },
    {
      "pid": "23",
      "size": 106556
    },
    {
      "pid": "24",
      "size": 114429
    },
    {
      "pid": "25",
      "size": 100583
    },
    {
      "pid": "26",
      "size": 134423
    },
    {
      "pid": "27",
      "size": 134423
    },
    {
      "pid": "28",
      "size": 134423
    },
    {
      "pid": "29",
      "size": 134423
    },
    {
      "pid": "41",
      "size": 106254
    },
    {
      "pid": "42",
      "size": 70107
    },
    {
      "pid": "43",
      "size": 94232
    },
    {
      "pid": "44",
      "size": 20535
    },
    {
      "pid": "45",
      "size": 134423
    },
    {
      "pid": "49",
      "size": 71615
    },
    {
      "pid": "50",
      "size": 20535
    },
    {
      "pid": "51",
      "size": 20535
    },
    {
      "pid": "52",
      "size": 102493
    },
    {
      "pid": "53",
      "size": 108408
    },
    {
      "pid": "64",
      "size": 84064
    },
    {
      "pid": "65",
      "size": 20535
    },
    {
      "pid": "66",
      "size": 20535
    }
  ],
  "extra_cameras": [
    {
      "key": "okinawa-city-hija",
      "name": "比謝川",
      "loc": "沖縄市（水位監視）",
      "size": 48102
    },
    {
      "key": "okinawa-city-awase1",
      "name": "泡瀬川①",
      "loc": "沖縄市（水位監視）",
      "size": 24233
    },
    {
      "key": "okinawa-city-awase2",
      "name": "泡瀬川②",
      "loc": "沖縄市（水位監視）",
      "size": 24512
    }
  ]
}