{
  "last_fetch_jst": "2026-03-30 23:53:58",
  "camera_count": 42,
  "cameras": [
    {
      "pid": "01",
      "size": 61135
    },
    {
      "pid": "02",
      "size": 53523
    },
    {
      "pid": "03",
      "size": 74585
    },
    {
      "pid": "04",
      "size": 50351
    },
    {
      "pid": "05",
      "size": 57817
    },
    {
      "pid": "06",
      "size": 39382
    },
    {
      "pid": "07",
      "size": 52709
    },
    {
      "pid": "08",
      "size": 46952
    },
    {
      "pid": "09",
      "size": 25243
    },
    {
      "pid": "10",
      "size": 38767
    },
    {
      "pid": "11",
      "size": 87251
    },
    {
      "pid": "12",
      "size": 52322
    },
    {
      "pid": "13",
      "size": 25294
    },
    {
      "pid": "14",
      "size": 134423
    },
    {
      "pid": "15",
      "size": 50759
    },
    {
      "pid": "16",
      "size": 5463
    },
    {
      "pid": "17",
      "size": 42387
    },
    {
      "pid": "18",
      "size": 28887
    },
    {
      "pid": "19",
      "size": 38322
    },
    {
      "pid": "20",
      "size": 60402
    },
    {
      "pid": "21",
      "size": 15692
    },
    {
      "pid": "22",
      "size": 49221
    },
    {
      "pid": "23",
      "size": 44408
    },
    {
      "pid": "24",
      "size": 53959
    },
    {
      "pid": "25",
      "size": 40149
    },
    {
      "pid": "26",
      "size": 134423
    },
    {
      "pid": "27",
      "size": 134423
    },
    {
      "pid": "28",
      "size": 134423
    },
    {
      "pid": "29",
      "size": 134423
    },
    {
      "pid": "41",
      "size": 69356
    },
    {
      "pid": "42",
      "size": 49803
    },
    {
      "pid": "43",
      "size": 5463
    },
    {
      "pid": "44",
      "size": 20535
    },
    {
      "pid": "45",
      "size": 134423
    },
    {
      "pid": "49",
      "size": 5463
    },
    {
      "pid": "50",
      "size": 20535
    },
    {
      "pid": "51",
      "size": 20535
    },
    {
      "pid": "52",
      "size": 44894
    },
    {
      "pid": "53",
      "size": 67879
    },
    {
      "pid": "64",
      "size": 5463
    },
    {
      "pid": "65",
      "size": 20535
    },
    {
      "pid": "66",
      "size": 20535
    }
  ],
  "extra_cameras": [
    {
      "key": "okinawa-city-hija",
      "name": "比謝川",
      "loc": "沖縄市（水位監視）",
      "size": 39281
    },
    {
      "key": "okinawa-city-awase1",
      "name": "泡瀬川①",
      "loc": "沖縄市（水位監視）",
      "size": 22921
    },
    {
      "key": "okinawa-city-awase2",
      "name": "泡瀬川②",
      "loc": "沖縄市（水位監視）",
      "size": 24247
    }
  ]
}