{
  "last_fetch_jst": "2026-07-03 21:19:57",
  "camera_count": 42,
  "cameras": [
    {
      "pid": "01",
      "size": 51761
    },
    {
      "pid": "02",
      "size": 61027
    },
    {
      "pid": "03",
      "size": 53701
    },
    {
      "pid": "04",
      "size": 56189
    },
    {
      "pid": "05",
      "size": 67630
    },
    {
      "pid": "06",
      "size": 46301
    },
    {
      "pid": "07",
      "size": 62365
    },
    {
      "pid": "08",
      "size": 49284
    },
    {
      "pid": "09",
      "size": 36194
    },
    {
      "pid": "10",
      "size": 45198
    },
    {
      "pid": "11",
      "size": 87571
    },
    {
      "pid": "12",
      "size": 84826
    },
    {
      "pid": "13",
      "size": 31846
    },
    {
      "pid": "14",
      "size": 134423
    },
    {
      "pid": "15",
      "size": 58243
    },
    {
      "pid": "16",
      "size": 83649
    },
    {
      "pid": "17",
      "size": 29676
    },
    {
      "pid": "18",
      "size": 30696
    },
    {
      "pid": "19",
      "size": 40525
    },
    {
      "pid": "20",
      "size": 64996
    },
    {
      "pid": "21",
      "size": 15692
    },
    {
      "pid": "22",
      "size": 70785
    },
    {
      "pid": "23",
      "size": 49791
    },
    {
      "pid": "24",
      "size": 59530
    },
    {
      "pid": "25",
      "size": 58513
    },
    {
      "pid": "26",
      "size": 134423
    },
    {
      "pid": "27",
      "size": 134423
    },
    {
      "pid": "28",
      "size": 134423
    },
    {
      "pid": "29",
      "size": 134423
    },
    {
      "pid": "41",
      "size": 64145
    },
    {
      "pid": "42",
      "size": 47210
    },
    {
      "pid": "43",
      "size": 56071
    },
    {
      "pid": "44",
      "size": 20535
    },
    {
      "pid": "45",
      "size": 134423
    },
    {
      "pid": "49",
      "size": 49936
    },
    {
      "pid": "50",
      "size": 20535
    },
    {
      "pid": "51",
      "size": 20535
    },
    {
      "pid": "52",
      "size": 45242
    },
    {
      "pid": "53",
      "size": 69490
    },
    {
      "pid": "64",
      "size": 47513
    },
    {
      "pid": "65",
      "size": 20535
    },
    {
      "pid": "66",
      "size": 20535
    }
  ],
  "extra_cameras": [
    {
      "key": "okinawa-city-hija",
      "name": "比謝川",
      "loc": "沖縄市（水位監視）",
      "size": 40910
    },
    {
      "key": "okinawa-city-awase1",
      "name": "泡瀬川①",
      "loc": "沖縄市（水位監視）",
      "size": 23795
    },
    {
      "key": "okinawa-city-awase2",
      "name": "泡瀬川②",
      "loc": "沖縄市（水位監視）",
      "size": 24568
    }
  ]
}