{
  "last_fetch_jst": "2026-06-19 19:01:13",
  "camera_count": 42,
  "cameras": [
    {
      "pid": "01",
      "size": 92490
    },
    {
      "pid": "02",
      "size": 92006
    },
    {
      "pid": "03",
      "size": 90478
    },
    {
      "pid": "04",
      "size": 108013
    },
    {
      "pid": "05",
      "size": 82337
    },
    {
      "pid": "06",
      "size": 93658
    },
    {
      "pid": "07",
      "size": 105702
    },
    {
      "pid": "08",
      "size": 87365
    },
    {
      "pid": "09",
      "size": 97253
    },
    {
      "pid": "10",
      "size": 72032
    },
    {
      "pid": "11",
      "size": 88219
    },
    {
      "pid": "12",
      "size": 95173
    },
    {
      "pid": "13",
      "size": 83823
    },
    {
      "pid": "14",
      "size": 134423
    },
    {
      "pid": "15",
      "size": 88931
    },
    {
      "pid": "16",
      "size": 104405
    },
    {
      "pid": "17",
      "size": 84251
    },
    {
      "pid": "18",
      "size": 93917
    },
    {
      "pid": "19",
      "size": 85879
    },
    {
      "pid": "20",
      "size": 63657
    },
    {
      "pid": "21",
      "size": 15692
    },
    {
      "pid": "22",
      "size": 105640
    },
    {
      "pid": "23",
      "size": 105228
    },
    {
      "pid": "24",
      "size": 114032
    },
    {
      "pid": "25",
      "size": 87765
    },
    {
      "pid": "26",
      "size": 134423
    },
    {
      "pid": "27",
      "size": 134423
    },
    {
      "pid": "28",
      "size": 134423
    },
    {
      "pid": "29",
      "size": 134423
    },
    {
      "pid": "41",
      "size": 74472
    },
    {
      "pid": "42",
      "size": 62667
    },
    {
      "pid": "43",
      "size": 91930
    },
    {
      "pid": "44",
      "size": 20535
    },
    {
      "pid": "45",
      "size": 134423
    },
    {
      "pid": "49",
      "size": 64799
    },
    {
      "pid": "50",
      "size": 20535
    },
    {
      "pid": "51",
      "size": 20535
    },
    {
      "pid": "52",
      "size": 89586
    },
    {
      "pid": "53",
      "size": 77948
    },
    {
      "pid": "64",
      "size": 76199
    },
    {
      "pid": "65",
      "size": 20535
    },
    {
      "pid": "66",
      "size": 20535
    }
  ],
  "extra_cameras": [
    {
      "key": "okinawa-city-hija",
      "name": "比謝川",
      "loc": "沖縄市（水位監視）",
      "size": 40539
    },
    {
      "key": "okinawa-city-awase1",
      "name": "泡瀬川①",
      "loc": "沖縄市（水位監視）",
      "size": 23959
    },
    {
      "key": "okinawa-city-awase2",
      "name": "泡瀬川②",
      "loc": "沖縄市（水位監視）",
      "size": 24378
    }
  ]
}