{
  "last_fetch_jst": "2026-05-18 00:04:25",
  "camera_count": 42,
  "cameras": [
    {
      "pid": "01",
      "size": 65976
    },
    {
      "pid": "02",
      "size": 59193
    },
    {
      "pid": "03",
      "size": 64048
    },
    {
      "pid": "04",
      "size": 48232
    },
    {
      "pid": "05",
      "size": 59396
    },
    {
      "pid": "06",
      "size": 37405
    },
    {
      "pid": "07",
      "size": 60221
    },
    {
      "pid": "08",
      "size": 44777
    },
    {
      "pid": "09",
      "size": 25515
    },
    {
      "pid": "10",
      "size": 42563
    },
    {
      "pid": "11",
      "size": 87185
    },
    {
      "pid": "12",
      "size": 63620
    },
    {
      "pid": "13",
      "size": 29137
    },
    {
      "pid": "14",
      "size": 134423
    },
    {
      "pid": "15",
      "size": 46223
    },
    {
      "pid": "16",
      "size": 88144
    },
    {
      "pid": "17",
      "size": 54134
    },
    {
      "pid": "18",
      "size": 27889
    },
    {
      "pid": "19",
      "size": 5463
    },
    {
      "pid": "20",
      "size": 50699
    },
    {
      "pid": "21",
      "size": 15692
    },
    {
      "pid": "22",
      "size": 53815
    },
    {
      "pid": "23",
      "size": 42116
    },
    {
      "pid": "24",
      "size": 34538
    },
    {
      "pid": "25",
      "size": 52818
    },
    {
      "pid": "26",
      "size": 134423
    },
    {
      "pid": "27",
      "size": 134423
    },
    {
      "pid": "28",
      "size": 134423
    },
    {
      "pid": "29",
      "size": 134423
    },
    {
      "pid": "41",
      "size": 72865
    },
    {
      "pid": "42",
      "size": 52356
    },
    {
      "pid": "43",
      "size": 5463
    },
    {
      "pid": "44",
      "size": 20535
    },
    {
      "pid": "45",
      "size": 134423
    },
    {
      "pid": "49",
      "size": 5463
    },
    {
      "pid": "50",
      "size": 20535
    },
    {
      "pid": "51",
      "size": 20535
    },
    {
      "pid": "52",
      "size": 43239
    },
    {
      "pid": "53",
      "size": 68481
    },
    {
      "pid": "64",
      "size": 5463
    },
    {
      "pid": "65",
      "size": 20535
    },
    {
      "pid": "66",
      "size": 20535
    }
  ],
  "extra_cameras": [
    {
      "key": "okinawa-city-hija",
      "name": "比謝川",
      "loc": "沖縄市（水位監視）",
      "size": 41108
    },
    {
      "key": "okinawa-city-awase1",
      "name": "泡瀬川①",
      "loc": "沖縄市（水位監視）",
      "size": 23561
    },
    {
      "key": "okinawa-city-awase2",
      "name": "泡瀬川②",
      "loc": "沖縄市（水位監視）",
      "size": 23922
    }
  ]
}